netbox_physical_clusters/__init__.py
netbox_physical_clusters/api/__init__.py
netbox_physical_clusters/api/nested_serializers.py
netbox_physical_clusters/api/serializers.py
netbox_physical_clusters/api/urls.py
netbox_physical_clusters/api/views.py
netbox_physical_clusters/choices.py
netbox_physical_clusters/core/__init__.py
netbox_physical_clusters/core/models/__init__.py
netbox_physical_clusters/filtersets.py
netbox_physical_clusters/forms/__init__.py
netbox_physical_clusters/forms/bulk_edit.py
netbox_physical_clusters/forms/bulk_import.py
netbox_physical_clusters/forms/filtersets.py
netbox_physical_clusters/forms/model_forms.py
netbox_physical_clusters/graphql/__init__.py
netbox_physical_clusters/graphql/schema.py
netbox_physical_clusters/graphql/types.py
netbox_physical_clusters/migrations/0001_initial.py
netbox_physical_clusters/migrations/0002_physicalcluster_and_more.py
netbox_physical_clusters/migrations/0003_physicalcluster_devices_physicalcluster_primary_ip4.py
netbox_physical_clusters/migrations/__init__.py
netbox_physical_clusters/models/__init__.py
netbox_physical_clusters/models/physical_cluster.py
netbox_physical_clusters/models/physical_cluster_type.py
netbox_physical_clusters/navigation.py
netbox_physical_clusters/search.py
netbox_physical_clusters/tables.py
netbox_physical_clusters/templates/netbox_physical_clusters/cluster_add_devices.html
netbox_physical_clusters/templates/netbox_physical_clusters/physical_cluster/base.html
netbox_physical_clusters/templates/netbox_physical_clusters/physical_cluster/devices.html
netbox_physical_clusters/templates/netbox_physical_clusters/physicalcluster.html
netbox_physical_clusters/templates/netbox_physical_clusters/physicalclustertype.html
netbox_physical_clusters/tests/__init__.py
netbox_physical_clusters/tests/test_filtersets.py
netbox_physical_clusters/tests/test_forms.py
netbox_physical_clusters/tests/test_graphql.py
netbox_physical_clusters/tests/test_models.py
netbox_physical_clusters/tests/test_views.py
netbox_physical_clusters-0.2.3.dist-info/LICENSE
netbox_physical_clusters-0.2.3.dist-info/METADATA
netbox_physical_clusters-0.2.3.dist-info/WHEEL
netbox_physical_clusters-0.2.3.dist-info/RECORD
