Metadata-Version: 2.1
Name: netbox-physical-clusters
Version: 0.2.3
Summary: A netbox plugin for managing multiple physical cluster types
Home-page: https://github.com/sapcc/netbox-physical-clusters
Keywords: Netbox,netbox,plugin
Author: Pat McLean
Author-email: patrick.mclean@sap.com
Requires-Python: >=3.10,<4.0
Classifier: Development Status :: 5 - Production/Stable
Classifier: Intended Audience :: Developers
Classifier: License :: OSI Approved :: Apache Software License
Classifier: Operating System :: OS Independent
Classifier: Programming Language :: Python :: 3
Classifier: Programming Language :: Python :: 3.10
Classifier: Programming Language :: Python :: 3.11
Project-URL: Documentation, https://sapcc.github.io/netbox-physical-clusters
